BDSpace/Space.cpython-39-darwin.so
BDSpace/Space.pxd
BDSpace/__init__.py
BDSpace/_version.py
BDSpace/Coordinates/Cartesian.cpython-39-darwin.so
BDSpace/Coordinates/Cartesian.pxd
BDSpace/Coordinates/__init__.py
BDSpace/Coordinates/transforms.cpython-39-darwin.so
BDSpace/Coordinates/transforms.pxd
BDSpace/Curve/Parametric.cpython-39-darwin.so
BDSpace/Curve/Parametric.pxd
BDSpace/Curve/__init__.py
BDSpace/Curve/_helpers.cpython-39-darwin.so
BDSpace/Curve/_helpers.pxd
BDSpace/Field/CurveField.cpython-39-darwin.so
BDSpace/Field/CurveField.pxd
BDSpace/Field/Field.cpython-39-darwin.so
BDSpace/Field/Field.pxd
BDSpace/Field/SphericallySymmetric.cpython-39-darwin.so
BDSpace/Field/SphericallySymmetric.pxd
BDSpace/Field/SuperposedField.cpython-39-darwin.so
BDSpace/Field/SuperposedField.pxd
BDSpace/Field/__init__.py
BDSpace/Figure/Cone.py
BDSpace/Figure/Cube.py
BDSpace/Figure/Cylinder.py
BDSpace/Figure/Sphere.py
BDSpace/Figure/Torus.py
BDSpace/Figure/__init__.py
BDSpace/Pathfinder/__init__.py
BDSpace-0.3.14.dist-info/LICENSE.txt
BDSpace-0.3.14.dist-info/METADATA
BDSpace-0.3.14.dist-info/NOTICE.txt
BDSpace-0.3.14.dist-info/WHEEL
BDSpace-0.3.14.dist-info/top_level.txt
BDSpace-0.3.14.dist-info/RECORD
