Metadata-Version: 2.1
Name: BDSpace
Version: 0.3.14
Summary: 3D space positioning and motion
Home-page: https://github.com/bond-anton/BDSpace
Author: Anton Bondarenko
Author-email: bond.anton@gmail.com
License: Apache Software License
Keywords: 3D coordinate Space paths trajectory
Platform: UNKNOWN
Classifier: Development Status :: 3 - Alpha
Classifier: Intended Audience :: Education
Classifier: Intended Audience :: Science/Research
Classifier: License :: OSI Approved :: Apache Software License
Classifier: Topic :: Scientific/Engineering :: Mathematics
Classifier: Programming Language :: Python
Classifier: Programming Language :: Python :: 3
Classifier: Programming Language :: Python :: 3.6
Classifier: Programming Language :: Python :: 3.7
Classifier: Programming Language :: Python :: 3.8
Classifier: Programming Language :: Python :: 3.9
Requires-Dist: numpy
Requires-Dist: scipy
Requires-Dist: BDQuaternions (>=0.2.11)
Requires-Dist: BDMesh (>=0.2.11)
